cockroachdb_cloud_client/__init__.py
cockroachdb_cloud_client/api/__init__.py
cockroachdb_cloud_client/api/cockroach_cloud/__init__.py
cockroachdb_cloud_client/api/cockroach_cloud/cockroach_cloud_add_allowlist_entry.py
cockroachdb_cloud_client/api/cockroach_cloud/cockroach_cloud_create_cluster.py
cockroachdb_cloud_client/api/cockroach_cloud/cockroach_cloud_create_database.py
cockroachdb_cloud_client/api/cockroach_cloud/cockroach_cloud_create_private_endpoint_services.py
cockroachdb_cloud_client/api/cockroach_cloud/cockroach_cloud_create_sql_user.py
cockroachdb_cloud_client/api/cockroach_cloud/cockroach_cloud_delete_allowlist_entry.py
cockroachdb_cloud_client/api/cockroach_cloud/cockroach_cloud_delete_cluster.py
cockroachdb_cloud_client/api/cockroach_cloud/cockroach_cloud_delete_database.py
cockroachdb_cloud_client/api/cockroach_cloud/cockroach_cloud_delete_log_export.py
cockroachdb_cloud_client/api/cockroach_cloud/cockroach_cloud_delete_sql_user.py
cockroachdb_cloud_client/api/cockroach_cloud/cockroach_cloud_edit_database.py
cockroachdb_cloud_client/api/cockroach_cloud/cockroach_cloud_enable_cmek_spec.py
cockroachdb_cloud_client/api/cockroach_cloud/cockroach_cloud_enable_log_export.py
cockroachdb_cloud_client/api/cockroach_cloud/cockroach_cloud_get_cluster.py
cockroachdb_cloud_client/api/cockroach_cloud/cockroach_cloud_get_cmek_cluster_info.py
cockroachdb_cloud_client/api/cockroach_cloud/cockroach_cloud_get_invoice.py
cockroachdb_cloud_client/api/cockroach_cloud/cockroach_cloud_get_log_export_info.py
cockroachdb_cloud_client/api/cockroach_cloud/cockroach_cloud_list_allowlist_entries.py
cockroachdb_cloud_client/api/cockroach_cloud/cockroach_cloud_list_available_regions.py
cockroachdb_cloud_client/api/cockroach_cloud/cockroach_cloud_list_aws_endpoint_connections.py
cockroachdb_cloud_client/api/cockroach_cloud/cockroach_cloud_list_cluster_nodes.py
cockroachdb_cloud_client/api/cockroach_cloud/cockroach_cloud_list_clusters.py
cockroachdb_cloud_client-2022.9.20.dist-info/LICENSE
cockroachdb_cloud_client-2022.9.20.dist-info/WHEEL
cockroachdb_cloud_client-2022.9.20.dist-info/METADATA
cockroachdb_cloud_client-2022.9.20.dist-info/RECORD
